allauth_2fa/__init__.py
allauth_2fa/adapter.py
allauth_2fa/app_settings.py
allauth_2fa/forms.py
allauth_2fa/middleware.py
allauth_2fa/mixins.py
allauth_2fa/py.typed
allauth_2fa/urls.py
allauth_2fa/utils.py
allauth_2fa/views.py
allauth_2fa/templates/allauth_2fa/authenticate.html
allauth_2fa/templates/allauth_2fa/backup_tokens.html
allauth_2fa/templates/allauth_2fa/remove.html
allauth_2fa/templates/allauth_2fa/setup.html
django_allauth_2fa_inventree-0.12.0a1.dist-info/METADATA
django_allauth_2fa_inventree-0.12.0a1.dist-info/WHEEL
django_allauth_2fa_inventree-0.12.0a1.dist-info/licenses/LICENSE
django_allauth_2fa_inventree-0.12.0a1.dist-info/RECORD
