Metadata-Version: 2.3
Name: django-allauth-2fa-inventree
Version: 0.12.0a1
Summary: Adds two factor authentication to django-allauth
Project-URL: Homepage, https://github.com/valohai/django-allauth-2fa
Author-email: Víðir Valberg Guðmundsson <valberg@orn.li>
License-Expression: Apache-2.0
License-File: LICENSE
Keywords: 2fa,allauth,auth,authentication,django,factor,otp,two
Classifier: Development Status :: 4 - Beta
Classifier: Environment :: Web Environment
Classifier: Framework :: Django
Classifier: Framework :: Django :: 4.1
Classifier: Framework :: Django :: 4.2
Classifier: Intended Audience :: Developers
Classifier: License :: OSI Approved :: Apache Software License
Classifier: Programming Language :: Python
Classifier: Programming Language :: Python :: 3.8
Classifier: Programming Language :: Python :: 3.9
Classifier: Programming Language :: Python :: 3.10
Classifier: Programming Language :: Python :: 3.11
Classifier: Topic :: Internet
Classifier: Topic :: Software Development :: Libraries :: Python Modules
Requires-Python: >=3.8
Requires-Dist: django-allauth<0.58.0,>=0.53.0
Requires-Dist: django-otp>=1.2.0
Requires-Dist: django>=4.1
Requires-Dist: qrcode>=5.3
Provides-Extra: docs
Requires-Dist: sphinx-autobuild==0.7.1; extra == 'docs'
Requires-Dist: sphinx-rtd-theme==0.2.4; extra == 'docs'
Requires-Dist: sphinx==1.6.5; extra == 'docs'
Provides-Extra: test
Requires-Dist: pytest-cov==4.1.0; extra == 'test'
Requires-Dist: pytest-django==4.5.2; extra == 'test'
